nextaddatamodule/__init__.py
nextaddatamodule/add.py
nextaddatamodule/dataapi/__init__.py
nextaddatamodule/dataapi/multiply.py
nextaddatamodule-0.0.2.dist-info/METADATA
nextaddatamodule-0.0.2.dist-info/WHEEL
nextaddatamodule-0.0.2.dist-info/top_level.txt
nextaddatamodule-0.0.2.dist-info/RECORD
